Workbook

Sheet Overview
B2: IT General Controls (ITGC) Assessment
B3: Meridian Group plc | Oracle ERP Cloud (Finance & Procurement)
B5: Engagement type | C5: Annual ITGC assessment supporting the FY2026 financial statement audit
B6: Assessment period | C6: 1 January 2026 to 30 September 2026 (interim)
B7: Scope | C7: Logical access, change management, system development and IT operations over the in-scope ERP and its hosting environment
B8: Framework basis | C8: COBIT 2019, NIST SP 800-53 and common SOX ITGC practice, mapped to the four standard control domains
B9: Assessor | C9: R. Khatri, IT Audit (illustrative worked example)
B10: Report date | C10: 3 October 2026
B11: Overall opinion | C11: Controls are partially effective. Two high-rated deficiencies require remediation before year-end reliance.
B13: How to use this workbook
B14: • Control Matrix - the full population of controls tested, with objective, risk, test procedure, result and rating. This is the working paper.
B15: • Findings Register - every control with an exception, written up as a deficiency with root cause, recommendation, owner and target date.
B16: • Dashboard - live roll-up of results and ratings by domain. The counts recalculate from the Control Matrix, so update the matrix and the numbers follow.
B17: • Legend - rating scales and the meaning of each result and status value. Read this before filling anything in.
B18: • To reuse this as a template: keep columns A to I, clear the test results in J onwards, and re-run your own testing.

Sheet Control Matrix
A1: Control ID | B1: Domain | C1: Control Objective | D1: Control Activity | E1: Risk if Control Fails | F1: Control Owner | G1: Frequency | H1: Type | I1: Nature | J1: Test Procedure | K1: Sample | L1: Result | M1: Exceptions Noted | N1: Finding Ref | O1: Risk Rating | P1: Status
A2: AC-01 | B2: A. Access to Programs & Data | C2: New user access is authorised before provisioning | D2: New starter access to the ERP is requested via the IT service portal and approved by the line manager and system owner before the account is created. | E2: Unauthorised accounts grant access to financial data and transactions. | F2: IT Security | G2: Per event | H2: Preventive | I2: IT-dependent manual | J2: For a sample of 25 joiners, inspect the ticket for documented manager and system-owner approval dated before account creation. | K2: 25 | L2: Effective | O2: Low | P2: Closed
A3: AC-02 | B3: A. Access to Programs & Data | C3: Leaver access is removed on a timely basis | D3: HR notifies IT of leavers; ERP accounts are disabled within one business day of the leaving date. | E3: Former staff retain access and can act on or exfiltrate financial data. | F3: IT Security | G3: Per event | H3: Preventive | I3: IT-dependent manual | J3: For 25 leavers, compare the HR leaving date to the account disable date in the admin log. Exception if removal exceeds one business day. | K3: 25 | L3: Partially Effective | M3: 3 of 25 leavers were disabled 4 to 9 days after their leaving date. No evidence of access being used in the gap. | N3: F-01 | O3: Medium | P3: In Progress
A4: AC-03 | B4: A. Access to Programs & Data | C4: User access is reviewed periodically | D4: System owners perform a quarterly recertification of all ERP user access; removals are actioned within five days of sign-off. | E4: Access creep and inappropriate standing access go undetected. | F4: System Owners | G4: Quarterly | H4: Detective | I4: Manual | J4: Inspect the Q1 and Q2 recertification evidence. Confirm completeness of the user list reviewed, sign-off, and that flagged removals were actioned. | K4: 2 | L4: Partially Effective | M4: Q1 review completed and signed. Q2 review was performed but sign-off is undated and two flagged accounts were not removed. | N4: F-02 | O4: Medium | P4: In Progress
A5: AC-04 | B5: A. Access to Programs & Data | C5: Privileged access is restricted and justified | D5: Administrator and super-user roles are limited to named IT staff, approved by the IT manager and documented in the privileged access register. | E5: Excessive privileged access enables unmonitored changes to data and configuration. | F5: IT Manager | G5: Per event | H5: Preventive | I5: Manual | J5: Obtain the list of privileged accounts. For each, confirm a business justification and current approval. Reconcile to the register. | K5: 12 | L5: Ineffective | M5: 8 privileged accounts exist against 5 approved. 3 belong to staff who changed role and no longer need admin rights. Register last updated 14 months ago. | N5: F-03 | O5: High | P5: Open
A6: AC-05 | B6: A. Access to Programs & Data | C6: Password and authentication settings meet policy | D6: ERP authentication enforces minimum length, complexity, lockout and MFA for remote and privileged access, configured to the IT security policy. | E6: Weak authentication allows account compromise and unauthorised access. | F6: IT Security | G6: Continuous | H6: Preventive | I6: Automated | J6: Extract the authentication configuration and compare each parameter to the documented policy. Confirm MFA is enforced for all remote sessions. | K6: 1 | L6: Effective | O6: Low | P6: Closed
A7: AC-06 | B7: A. Access to Programs & Data | C7: Segregation of duties is enforced in roles | D7: ERP roles are designed so that no single user can both create and approve a payment, or create a vendor and process a payment to it. | E7: SoD conflicts enable fraud and unauthorised disbursements. | F7: Finance Systems | G7: Continuous | H7: Preventive | I7: Automated | J7: Run the SoD ruleset against current role assignments. Investigate each flagged conflict for a documented mitigating control. | K7: 1 | L7: Partially Effective | M7: 4 users hold conflicting create-and-approve payment access. 2 have documented monitoring; 2 do not. | N7: F-04 | O7: High | P7: Open
A8: AC-07 | B8: A. Access to Programs & Data | C8: Generic and service accounts are controlled | D8: Shared, generic and service accounts are inventoried, owned, and their passwords vaulted with access logged. | E8: Shared accounts break accountability and are a common attack path. | F8: IT Security | G8: Quarterly | H8: Detective | I8: Manual | J8: Obtain the service account inventory. Confirm each has a named owner and vaulted credentials. Sample 5 for last password rotation. | K8: 5 | L8: Effective | O8: Low | P8: Closed
A9: AC-08 | B9: A. Access to Programs & Data | C9: Database and OS access to the ERP is restricted | D9: Direct database and operating-system access to the ERP platform is limited to platform administrators and logged. | E9: Back-end access bypasses application controls over financial data. | F9: Infrastructure | G9: Continuous | H9: Preventive | I9: IT-dependent manual | J9: Review the list of accounts with direct DB and OS access. Confirm each is a platform admin and that logging is enabled. | K9: 6 | L9: Effective | O9: Low | P9: Closed
A10: AC-09 | B10: A. Access to Programs & Data | C10: Physical access to hosting is restricted | D10: The ERP is hosted in a certified cloud region; physical security is inherited and evidenced by the provider's SOC 2 Type II report. | E10: Unrestricted physical access risks tampering and data loss. | F10: Infrastructure | G10: Annual | H10: Preventive | I10: Manual | J10: Obtain the provider's current SOC 2 Type II report. Confirm physical security controls are in scope and the opinion is unqualified. | K10: 1 | L10: Effective | O10: Low | P10: Closed
A11: AC-10 | B11: A. Access to Programs & Data | C11: Access to financial reports is role-appropriate | D11: Reporting and data-extract roles are restricted to finance and approved analysts on a least-privilege basis. | E11: Over-broad reporting access exposes sensitive financial data. | F11: Finance Systems | G11: Quarterly | H11: Detective | I11: Manual | J11: Sample 15 users with reporting roles and confirm role-appropriateness against their job function. | K11: 15 | L11: Effective | O11: Low | P11: Closed
A12: AC-11 | B12: A. Access to Programs & Data | C12: Terminated privileged access is revoked immediately | D12: Privileged accounts for leavers are revoked on the leaving date, ahead of standard user removal. | E12: Retained admin access post-departure is a severe exposure. | F12: IT Security | G12: Per event | H12: Preventive | I12: IT-dependent manual | J12: For all privileged-user leavers in the period, confirm same-day revocation. | K12: 3 | L12: Effective | O12: Low | P12: Closed
A13: AC-12 | B13: A. Access to Programs & Data | C13: Access logs are monitored for anomalies | D13: Failed logins, privileged actions and out-of-hours access are logged to the SIEM and reviewed against alerting rules. | E13: Unmonitored access means intrusions and misuse go undetected. | F13: SOC | G13: Continuous | H13: Detective | I13: Automated | J13: Confirm ERP logs feed the SIEM. Inspect 4 weeks of alert handling for privileged-action and failed-login rules. | K13: 4 | L13: Effective | O13: Low | P13: Closed
A14: CM-01 | B14: B. Program Changes | C14: Changes are authorised before development | D14: ERP configuration and code changes are raised as change records and approved by the change advisory board before work begins. | E14: Unauthorised changes can introduce errors or malicious logic to financial processing. | F14: Change Manager | G14: Per event | H14: Preventive | I14: IT-dependent manual | J14: For 25 changes, inspect the change record for CAB approval dated before development started. | K14: 25 | L14: Effective | O14: Low | P14: Closed
A15: CM-02 | B15: B. Program Changes | C15: Changes are tested and results documented | D15: Each change is tested in a non-production environment and the test results are recorded and reviewed before approval to deploy. | E15: Untested changes can corrupt data or break financial controls. | F15: QA Lead | G15: Per event | H15: Preventive | I15: Manual | J15: For the 25 changes, inspect retained test evidence and reviewer sign-off. | K15: 25 | L15: Partially Effective | M15: 2 of 25 changes had no retained test evidence, though both were low-risk config changes. | N15: F-05 | O15: Low | P15: In Progress
A16: CM-03 | B16: B. Program Changes | C16: User acceptance and deployment are approved | D16: Business owners provide UAT sign-off and deployment is approved before release to production. | E16: Changes reach production without business validation. | F16: Business Owner | G16: Per event | H16: Preventive | I16: Manual | J16: For the sample, inspect UAT sign-off and deployment approval. | K16: 25 | L16: Effective | O16: Low | P16: Closed
A17: CM-04 | B17: B. Program Changes | C17: Developers cannot deploy their own changes to production | D17: Deployment to production is performed by a separate release function; developers have no production deploy rights. | E17: A single person able to write and release code can bypass review. | F17: Release Mgmt | G17: Continuous | H17: Preventive | I17: Automated | J17: Review production deploy permissions and reconcile against the developer list to confirm separation. | K17: 1 | L17: Ineffective | M17: 2 developers retain production deploy access in the pipeline, breaking segregation between build and release. | N17: F-06 | O17: High | P17: Open
A18: CM-05 | B18: B. Program Changes | C18: Emergency changes follow a controlled path | D18: Emergency changes are deployed under a break-glass procedure and retrospectively approved within two business days. | E18: Emergency fixes bypass controls without later scrutiny. | F18: Change Manager | G18: Per event | H18: Detective | I18: Manual | J18: For all emergency changes in the period, confirm retrospective approval within SLA. | K18: 4 | L18: Effective | O18: Low | P18: Closed
A19: CM-06 | B19: B. Program Changes | C19: Non-production and production environments are segregated | D19: Development, test and production are separate environments with no shared credentials. | E19: Shared environments risk unreviewed code reaching production. | F19: Infrastructure | G19: Continuous | H19: Preventive | I19: Automated | J19: Confirm environment separation and that no credentials are shared across tiers. | K19: 1 | L19: Effective | O19: Low | P19: Closed
A20: CM-07 | B20: B. Program Changes | C20: Vendor patches are assessed and applied | D20: Vendor-released patches and quarterly ERP updates are assessed, tested and applied within the defined window. | E20: Unpatched systems carry known vulnerabilities. | F20: Infrastructure | G20: Quarterly | H20: Preventive | I20: IT-dependent manual | J20: For the two update cycles in the period, confirm assessment, testing and timely application. | K20: 2 | L20: Effective | O20: Low | P20: Closed
A21: CM-08 | B21: B. Program Changes | C21: Change records are complete and traceable | D21: Every production change maps to an approved change record; no unlogged changes appear in deployment logs. | E21: Untracked changes undermine the whole change process. | F21: Change Manager | G21: Monthly | H21: Detective | I21: IT-dependent manual | J21: Reconcile production deployment logs for 2 months to approved change records. Investigate unmatched entries. | K21: 2 | L21: Partially Effective | M21: Deployment log shows 1 change with no matching record; traced to a config fix logged late. | N21: F-07 | O21: Medium | P21: In Progress
A22: SD-01 | B22: C. Program Development | C22: New projects are approved before development | D22: New system and major-enhancement projects are approved by a steering group with defined scope and budget. | E22: Unapproved development wastes resource and bypasses governance. | F22: IT Steering | G22: Per event | H22: Preventive | I22: Manual | J22: For the one in-scope implementation project, inspect steering-group approval and scope. | K22: 1 | L22: Effective | O22: Low | P22: Closed
A23: SD-02 | B23: C. Program Development | C23: Requirements and design are documented and approved | D23: Functional and technical designs are documented and signed off by business and IT before build. | E23: Poorly specified builds fail to meet control requirements. | F23: Project Lead | G23: Per event | H23: Preventive | I23: Manual | J23: Inspect requirements and design documents with approvals for the project. | K23: 1 | L23: Effective | O23: Low | P23: Closed
A24: SD-03 | B24: C. Program Development | C24: Data conversion is controlled and reconciled | D24: Data migrated into the ERP is reconciled to source, with record counts and control totals signed off. | E24: Migration errors corrupt opening financial balances. | F24: Data Lead | G24: Per event | H24: Detective | I24: IT-dependent manual | J24: Inspect the migration reconciliation, control totals and sign-off. | K24: 1 | L24: Effective | O24: Low | P24: Closed
A25: SD-04 | B25: C. Program Development | C25: Go-live is formally approved | D25: A go-live decision is made against defined readiness criteria and signed off before production cutover. | E25: Premature go-live releases an unready system. | F25: IT Steering | G25: Per event | H25: Preventive | I25: Manual | J25: Inspect the go-live checklist and sign-off against readiness criteria. | K25: 1 | L25: Partially Effective | M25: Go-live was approved, but 2 of 9 readiness criteria were open at sign-off with no documented risk acceptance. | N25: F-08 | O25: Low | P25: In Progress
A26: SD-05 | B26: C. Program Development | C26: Developers are segregated from production data | D26: Development uses masked or synthetic data; developers have no standing access to production financial data. | E26: Developer access to live data risks leakage and unreviewed change. | F26: Infrastructure | G26: Continuous | H26: Preventive | I26: Automated | J26: Confirm non-production uses masked data and review developer access to production data stores. | K26: 1 | L26: Effective | O26: Low | P26: Closed
A27: OP-01 | B27: D. Computer Operations | C27: Batch jobs are scheduled and monitored | D27: Financial batch jobs run on an approved schedule; failures raise alerts and are resolved and documented. | E27: Failed or missed jobs leave financial data incomplete. | F27: IT Operations | G27: Daily | H27: Detective | I27: Automated | J27: For 4 weeks, inspect the job monitor for failures and confirm each was resolved and documented. | K27: 4 | L27: Effective | O27: Low | P27: Closed
A28: OP-02 | B28: D. Computer Operations | C28: Backups run and are verified | D28: ERP data is backed up on schedule; backup success is monitored and failures investigated. | E28: Backup failure risks irrecoverable loss of financial data. | F28: IT Operations | G28: Daily | H28: Detective | I28: Automated | J28: Inspect backup logs for 4 weeks. Confirm success monitoring and follow-up on any failures. | K28: 4 | L28: Effective | O28: Low | P28: Closed
A29: OP-03 | B29: D. Computer Operations | C29: Backup restores are tested | D29: A restore test is performed at least annually and the result documented. | E29: Backups that cannot be restored provide false assurance. | F29: IT Operations | G29: Annual | H29: Detective | I29: Manual | J29: Obtain evidence of the most recent restore test and its outcome. | K29: 1 | L29: Ineffective | M29: No restore test has been performed in the last 18 months. Recoverability is unproven. | N29: F-09 | O29: Medium | P29: Open
A30: OP-04 | B30: D. Computer Operations | C30: Incidents are logged, triaged and resolved | D30: IT incidents affecting the ERP are logged, prioritised and resolved within SLA, with major incidents reviewed. | E30: Unmanaged incidents prolong outages and errors. | F30: Service Desk | G30: Per event | H30: Detective | I30: IT-dependent manual | J30: Sample 15 ERP incidents and confirm logging, prioritisation and SLA resolution. | K30: 15 | L30: Effective | O30: Low | P30: Closed
A31: OP-05 | B31: D. Computer Operations | C31: Problem management addresses recurring issues | D31: Recurring incidents are raised as problems and root-caused to prevent recurrence. | E31: Repeat failures persist without root-cause analysis. | F31: IT Operations | G31: Monthly | H31: Detective | I31: Manual | J31: Inspect the problem register and confirm recurring incidents were escalated and root-caused. | K31: 3 | L31: Effective | O31: Low | P31: Closed
A32: OP-06 | B32: D. Computer Operations | C32: Capacity and availability are monitored | D32: System performance, capacity and availability are monitored against thresholds with alerting. | E32: Capacity exhaustion causes outages during financial processing. | F32: Infrastructure | G32: Continuous | H32: Detective | I32: Automated | J32: Confirm monitoring thresholds and review a month of capacity alerts and responses. | K32: 1 | L32: Effective | O32: Low | P32: Closed
A33: OP-07 | B33: D. Computer Operations | C33: Disaster recovery is defined and tested | D33: A documented DR plan exists for the ERP with defined RTO and RPO, and is tested periodically. | E33: An untested DR plan may fail in a real outage. | F33: IT Operations | G33: Annual | H33: Preventive | I33: Manual | J33: Inspect the DR plan, confirm RTO and RPO are defined, and obtain evidence of the last DR test. | K33: 1 | L33: Partially Effective | M33: DR plan exists with defined RTO and RPO, but the last full test was 20 months ago, outside the annual policy. | N33: F-10 | O33: Medium | P33: In Progress

Sheet Findings Register
A1: Finding | B1: Control ID | C1: Domain | D1: Deficiency | E1: Root Cause | F1: Recommendation | G1: Risk Rating | H1: Owner | I1: Target Date | J1: Status
A2: F-03 | B2: AC-04 | C2: Access | D2: 8 privileged accounts exist against 5 approved; 3 holders no longer require admin rights and the register is 14 months stale. | E2: No periodic review of privileged access; the register is not maintained as an active control. | F2: Remove the 3 unneeded admin accounts now. Introduce a quarterly privileged-access review tied to the register, with IT-manager sign-off. | G2: High | H2: IT Manager | I2: 31 Oct 2026 | J2: Open
A3: F-06 | B3: CM-04 | C3: Changes | D3: 2 developers retain production deploy access, breaking separation between code authoring and release. | E3: Pipeline roles were not re-scoped after a tooling migration; deploy rights were over-granted. | F3: Revoke developer production-deploy rights and route all releases through the release function. Add a recurring access reconciliation. | G3: High | H3: Release Mgmt | I3: 15 Oct 2026 | J3: Open
A4: F-04 | B4: AC-06 | C4: Access | D4: 4 users hold create-and-approve payment access; 2 have no documented mitigating control. | E4: Role design permits the conflict and the SoD review does not consistently require a mitigating control. | F4: Remediate the 2 unmitigated conflicts by role change or documented monitoring. Build SoD conflicts into the access-review step. | G4: High | H4: Finance Systems | I4: 31 Oct 2026 | J4: Open
A5: F-09 | B5: OP-03 | C5: Operations | D5: No backup restore test in 18 months; recoverability of ERP data is unproven. | E5: Restore testing is not scheduled as a recurring operational task. | F5: Perform a full restore test this quarter and document the outcome. Schedule restore tests at least annually. | G5: Medium | H5: IT Operations | I5: 30 Nov 2026 | J5: Open
A6: F-10 | B6: OP-07 | C6: Operations | D6: DR plan exists with RTO and RPO defined, but the last full test was 20 months ago. | E6: DR testing cadence slipped and was not tracked against the annual policy. | F6: Run a DR test before year-end and set an annual recurring schedule with results reviewed by IT management. | G6: Medium | H6: IT Operations | I6: 15 Dec 2026 | J6: In Progress
A7: F-01 | B7: AC-02 | C7: Access | D7: 3 of 25 leavers were disabled 4 to 9 days late. No evidence of misuse in the gap. | E7: Reliance on manual HR-to-IT handoff with no automated trigger or exception alert. | F7: Add an automated leaver trigger from HR to IT and a weekly exception report for accounts not disabled on the leaving date. | G7: Medium | H7: IT Security | I7: 30 Nov 2026 | J7: In Progress
A8: F-02 | B8: AC-03 | C8: Access | D8: Q2 access recertification sign-off is undated and 2 flagged accounts were not removed. | E8: Review is performed but the evidence standard and follow-through on removals are not enforced. | F8: Re-run the Q2 review to a defined checklist, remove the flagged accounts, and require dated sign-off with action tracking. | G8: Medium | H8: System Owners | I8: 14 Nov 2026 | J8: In Progress
A9: F-07 | B9: CM-08 | C9: Changes | D9: Deployment log shows 1 change with no matching approved record (late-logged config fix). | E9: A config fix was deployed before the change record was raised, breaking traceability. | F9: Reinforce no-record-no-deploy at the pipeline gate and reconcile logs to records monthly. | G9: Medium | H9: Change Manager | I9: 21 Nov 2026 | J9: In Progress
A10: F-05 | B10: CM-02 | C10: Changes | D10: 2 of 25 changes had no retained test evidence (both low-risk config changes). | E10: Test evidence is not consistently attached to the change record for minor changes. | F10: Require test evidence or a documented low-risk waiver on every change record before approval. | G10: Low | H10: QA Lead | I10: 30 Nov 2026 | J10: In Progress
A11: F-08 | B11: SD-04 | C11: Development | D11: Go-live approved with 2 of 9 readiness criteria open and no documented risk acceptance. | E11: Readiness gate allowed sign-off without recording acceptance of open items. | F11: Require explicit documented risk acceptance for any open readiness criterion at go-live. | G11: Low | H11: IT Steering | I11: N/A (post-event) | J11: In Progress

Sheet Dashboard
B2: ITGC Assessment Dashboard
B3: Live roll-up from the Control Matrix. Figures recalculate when the matrix changes.
B5: Controls Tested | D5: Effective | F5: Partially Effective
B6: =COUNTA('Control Matrix'!$A$2:$A$33) -> 32 | D6: =COUNTIF('Control Matrix'!$L$2:$L$33,"Effective") -> 22 | F6: =COUNTIF('Control Matrix'!$L$2:$L$33,"Partially Effective") -> 7
B8: Ineffective | D8: Open Findings | F8: High-Rated Deficiencies
B9: =COUNTIF('Control Matrix'!$L$2:$L$33,"Ineffective") -> 3 | D9: =COUNTIF('Control Matrix'!$P$2:$P$33,"Open") -> 4 | F9: =COUNTIF('Control Matrix'!$O$2:$O$33,"High") -> 3
B12: Results by Control Domain
B13: Domain | C13: Tested | D13: Effective | E13: Partial | F13: Ineffective | G13: % Effective
B14: Access to Programs & Data | C14: =COUNTIF('Control Matrix'!$B$2:$B$33,"A. Access to Programs & Data") -> 12 | D14: =COUNTIFS('Control Matrix'!$B$2:$B$33,"A. Access to Programs & Data",'Control Matrix'!$L$2:$L$33,"Effective") -> 8 | E14: =COUNTIFS('Control Matrix'!$B$2:$B$33,"A. Access to Programs & Data",'Control Matrix'!$L$2:$L$33,"Partially Effective") -> 3 | F14: =COUNTIFS('Control Matrix'!$B$2:$B$33,"A. Access to Programs & Data",'Control Matrix'!$L$2:$L$33,"Ineffective") -> 1 | G14: =IFERROR(D14/C14,0) -> 0.66666667
B15: Program Changes | C15: =COUNTIF('Control Matrix'!$B$2:$B$33,"B. Program Changes") -> 8 | D15: =COUNTIFS('Control Matrix'!$B$2:$B$33,"B. Program Changes",'Control Matrix'!$L$2:$L$33,"Effective") -> 5 | E15: =COUNTIFS('Control Matrix'!$B$2:$B$33,"B. Program Changes",'Control Matrix'!$L$2:$L$33,"Partially Effective") -> 2 | F15: =COUNTIFS('Control Matrix'!$B$2:$B$33,"B. Program Changes",'Control Matrix'!$L$2:$L$33,"Ineffective") -> 1 | G15: =IFERROR(D15/C15,0) -> 0.625
B16: Program Development | C16: =COUNTIF('Control Matrix'!$B$2:$B$33,"C. Program Development") -> 5 | D16: =COUNTIFS('Control Matrix'!$B$2:$B$33,"C. Program Development",'Control Matrix'!$L$2:$L$33,"Effective") -> 4 | E16: =COUNTIFS('Control Matrix'!$B$2:$B$33,"C. Program Development",'Control Matrix'!$L$2:$L$33,"Partially Effective") -> 1 | F16: =COUNTIFS('Control Matrix'!$B$2:$B$33,"C. Program Development",'Control Matrix'!$L$2:$L$33,"Ineffective") -> 0 | G16: =IFERROR(D16/C16,0) -> 0.8
B17: Computer Operations | C17: =COUNTIF('Control Matrix'!$B$2:$B$33,"D. Computer Operations") -> 7 | D17: =COUNTIFS('Control Matrix'!$B$2:$B$33,"D. Computer Operations",'Control Matrix'!$L$2:$L$33,"Effective") -> 5 | E17: =COUNTIFS('Control Matrix'!$B$2:$B$33,"D. Computer Operations",'Control Matrix'!$L$2:$L$33,"Partially Effective") -> 1 | F17: =COUNTIFS('Control Matrix'!$B$2:$B$33,"D. Computer Operations",'Control Matrix'!$L$2:$L$33,"Ineffective") -> 1 | G17: =IFERROR(D17/C17,0) -> 0.71428571
B18: Total | C18: =SUM(C14:C17) -> 32 | D18: =SUM(D14:D17) -> 22 | E18: =SUM(E14:E17) -> 7 | F18: =SUM(F14:F17) -> 3 | G18: =IFERROR(D18/C18,0) -> 0.6875
B21: Deficiencies by Risk Rating
B22: Rating | C22: Count
B23: High | C23: =COUNTIF('Control Matrix'!$O$2:$O$33,"High") -> 3
B24: Medium | C24: =COUNTIF('Control Matrix'!$O$2:$O$33,"Medium") -> 5
B25: Low | C25: =COUNTIF('Control Matrix'!$O$2:$O$33,"Low") -> 24

Sheet Legend
B2: Legend & Rating Scales
B4: Test result
B5: Effective | C5: Control is designed appropriately and operated without exception across the sample.
B6: Partially Effective | C6: Control operates but with exceptions or design gaps that reduce reliance.
B7: Ineffective | C7: Control is absent, not operating, or failed such that no reliance is possible.
B8: Not Tested | C8: Control in scope but not yet tested in this cycle.
B10: Risk rating of a deficiency
B11: High | C11: Direct risk to the integrity of financial data or a broken segregation of duties. Remediate before year-end reliance.
B12: Medium | C12: Control weakness with a plausible path to error or misuse. Remediate on a defined timeline.
B13: Low | C13: Minor or isolated gap with limited impact. Address as housekeeping.
B15: Status
B16: Open | C16: Deficiency identified, remediation not yet started.
B17: In Progress | C17: Remediation under way, not yet verified.
B18: Closed | C18: Remediation complete and verified by re-test.
B19: N/A | C19: Not applicable, for example a one-off past event with no ongoing control.
B21: Control type and nature
B22: Preventive | C22: Stops an error or unauthorised act before it happens.
B23: Detective | C23: Identifies an error or issue after it has occurred.
B24: Automated | C24: Performed by the system based on configuration.
B25: IT-dependent manual | C25: A manual control that relies on system-generated information.
B26: Manual | C26: Performed by a person without a system dependency.
B28: Domains
B29: A. Access to Programs & Data | C29: Who can get into the system and data, and what they can do once in.
B30: B. Program Changes | C30: How changes to the live system are requested, tested, approved and released.
B31: C. Program Development | C31: How new systems and major enhancements are built and brought live.
B32: D. Computer Operations | C32: How the system is run day to day: jobs, backups, incidents, recovery.
